[
    {
     "title": "APT.",
     "name": "로제 (ROS?) & Bruno Mars",
     "atmos": "잔잔한"
     },

    {
     "title": "Whiplash",
     "name": "aespa",
     "atmos": "신나는"
     },

    {
     "title": "UP (KARINA Solo)",
     "name": "aespa",
     "atmos": "벅차오르는"
     },

    {
     "title": "Supersonic",
     "name": "프로미스나인",
     "atmos": "신나는"
     },

    {
     "title": "CRAZY",
     "name": "LE SSERAFIM (르세라핌)",
     "atmos": "신나는"
     },

    {
     "title": "Supernatural",
     "name": "NewJeans",
     "atmos": "잔잔한"
     },

    {
     "title": "HAPPY",
     "name": "DAY6 (데이식스)",
     "atmos": "신나는"
     },

    {
     "title": "내 이름 맑음",
     "name": "QWER",
     "atmos": "잔잔한"
     },

    {
     "title": "How Sweet",
     "name": "NewJeans",
     "atmos": "신나는"
     },

    {
     "title": "클락션 (Klaxon)",
     "name": "(여자)아이들",
     "atmos": "벅차오르는"
     },

    {
     "title": "Small girl (feat. 도경수(D.O.))",
     "name": "이영지",
     "atmos": "잔잔한"
     },

    {
     "title": "Sticky",
     "name": "KISS OF LIFE",
     "atmos": "신나는"
     },

    {
     "title": "Magnetic",
     "name": "아일릿 (ILLIT)",
     "atmos": "신나는"
     },

    {
     "title": "Supernova",
     "name": "aespa",
     "atmos": "벅차오르는"
     },

    {
     "title": "해야 (HEYA)",
     "name": "IVE (아이브)",
     "atmos": "벅차오르는"
     },

    {
     "title": "나는 아픈 건 딱 질색이니까",
     "name": "(여자)아이들",
     "atmos": "슬픈"
     },

    {
     "title": "첫 만남은 계획대로 되지 않아",
     "name": "TWS (투어스)",
     "atmos": "잔잔한"
     },

    {
     "title": "SHEESH",
     "name": "BABYMONSTER",
     "atmos": "신나는"
     },

    {
     "title": "Baddie",
     "name": "IVE (아이브)",
     "atmos": "신나는"
     },

    {
     "title": "Super Shy",
     "name": "NewJeans",
     "atmos": "신나는"
     },

    {
     "title": "Spicy",
     "name": "aespa",
     "atmos": "벅차오르는"
     },

    {
     "title": "이브, 프시케 그리고 푸른 수염의 아내",
     "name": "LE SSERAFIM (르세라핌)",
     "atmos": "벅차오르는"
     },

    {
     "title": "Love Me Like This",
     "name": "NMIXX",
     "atmos": "신나는"
     },

    {
     "title": "I AM",
     "name": "IVE (아이브)",
     "atmos": "벅차오르는"
     },

    {
     "title": "꽃",
     "name": "지수 (JISOO)",
     "atmos": "잔잔한"
     },

    {
     "title": "OMG",
     "name": "NewJeans",
     "atmos": "신나는"
     },

    {
     "title": "KNOCK",
     "name": "이채연",
     "atmos": "벅차오르는"
     },

    {
     "title": "UNFORGIVEN (feat. Nile Rodgers)",
     "name": "LE SSERAFIM (르세라핌)",
     "atmos": "벅차오르는"
     },

    {
     "title": "Kitsch",
     "name": "IVE (아이브)",
     "atmos": "신나는"
     },

    {
     "title": "Ditto",
     "name": "NewJeans",
     "atmos": "잔잔한"
     },

    {
     "title": "Hype Boy",
     "name": "NewJeans",
     "atmos": "신나는"
     },

    {
     "title": "LOVE DIVE",
     "name": "IVE (아이브)",
     "atmos": "벅차오르는"
     }
]
